dungeon_game_mykhailovskyi/__init__.py
dungeon_game_mykhailovskyi/game_enemy.py
dungeon_game_mykhailovskyi/game_exceptions.py
dungeon_game_mykhailovskyi/game_map.py
dungeon_game_mykhailovskyi/game_world.py
dungeon_game_mykhailovskyi/logging_utility.py
dungeon_game_mykhailovskyi/main.py
dungeon_game_mykhailovskyi/map_generator.py
dungeon_game_mykhailovskyi/player.py
dungeon_game_mykhailovskyi/savegame_utility.py
dungeon_game_mykhailovskyi-0.1.6.dist-info/LICENSE.txt
dungeon_game_mykhailovskyi-0.1.6.dist-info/METADATA
dungeon_game_mykhailovskyi-0.1.6.dist-info/WHEEL
dungeon_game_mykhailovskyi-0.1.6.dist-info/top_level.txt
dungeon_game_mykhailovskyi-0.1.6.dist-info/RECORD
