Metadata-Version: 2.1
Name: dungeon-game-mykhailovskyi
Version: 0.1.6
Summary: Console game made during Python learning.
Home-page: https://github.com/vonKleve/campus_2018_python
Author: Mykhailovskyi Oleksandr
Author-email: UNKNOWN
License: MIT
Platform: UNKNOWN
